pygitx/__init__.py
pygitx/__init__.pyi
pygitx/_native.abi3.so
pygitx-0.2.2.dist-info/METADATA
pygitx-0.2.2.dist-info/WHEEL
pygitx-0.2.2.dist-info/licenses/LICENSE
pygitx-0.2.2.dist-info/RECORD
