Metadata-Version: 2.4
Name: pygitx
Version: 0.2.2
Classifier: Programming Language :: Python :: 3.11
Classifier: Programming Language :: Python :: 3.12
Classifier: Programming Language :: Python :: 3.13
Classifier: Programming Language :: Python :: 3.14
Classifier: Programming Language :: Rust
Classifier: Operating System :: MacOS
Classifier: Operating System :: POSIX :: Linux
Classifier: Operating System :: Microsoft :: Windows
Classifier: Topic :: Software Development :: Version Control
Requires-Dist: maturin ; extra == 'dev'
Requires-Dist: pytest ; extra == 'dev'
Requires-Dist: pytest-cov ; extra == 'dev'
Provides-Extra: dev
License-File: LICENSE
Summary: Cross-platform Git history access via Rust with a Python API
Author-email: Jiucheng Zang <git.jiucheng@gmail.com>
License-Expression: Apache-2.0
Requires-Python: >=3.11
Project-URL: Documentation, https://zangjiucheng.github.io/pygitx
Project-URL: Homepage, https://github.com/zangjiucheng/pygitx
